treemapper/__init__.py
treemapper/__main__.py
treemapper/cli.py
treemapper/ignore.py
treemapper/logger.py
treemapper/tree.py
treemapper/treemapper.py
treemapper/version.py
treemapper/writer.py
treemapper-1.1.3.dist-info/licenses/LICENSE
treemapper-1.1.3.dist-info/METADATA
treemapper-1.1.3.dist-info/WHEEL
treemapper-1.1.3.dist-info/entry_points.txt
treemapper-1.1.3.dist-info/top_level.txt
treemapper-1.1.3.dist-info/RECORD
