Metadata-Version: 2.4
Name: treemapper
Version: 1.1.3
Summary: Export codebase structure and contents for AI/LLM context
Author-email: Nikolay Eremeev <nikolay.eremeev@outlook.com>
License:                                  Apache License
Project-URL: Homepage, https://github.com/nikolay-e/treemapper
Keywords: code-analysis,directory-tree,yaml,json,llm,ai,codebase,context,chatgpt,claude,code-context,export,tree
Classifier: Development Status :: 5 - Production/Stable
Classifier: Environment :: Console
Classifier: Intended Audience :: Developers
Classifier: Programming Language :: Python :: 3
Classifier: Programming Language :: Python :: 3.9
Classifier: Programming Language :: Python :: 3.10
Classifier: Programming Language :: Python :: 3.11
Classifier: Programming Language :: Python :: 3.12
Classifier: Programming Language :: Python :: 3.13
Classifier: License :: OSI Approved :: Apache Software License
Classifier: Operating System :: OS Independent
Classifier: Topic :: Software Development :: Libraries :: Python Modules
Classifier: Topic :: Utilities
Classifier: Typing :: Typed
Requires-Python: >=3.9
License-File: LICENSE
Requires-Dist: pathspec<2.0,>=0.11
Requires-Dist: pyyaml<8.0,>=6.0.2
Provides-Extra: dev
Requires-Dist: pytest<9.0,>=7.0; extra == "dev"
Requires-Dist: pytest-cov<8.0,>=3.0; extra == "dev"
Requires-Dist: pytest-xdist<4.0,>=3.0; extra == "dev"
Requires-Dist: hypothesis<7.0,>=6.0; extra == "dev"
Requires-Dist: mutmut<4.0,>=2.0; extra == "dev"
Requires-Dist: coverage<8.0,>=7.0; extra == "dev"
Requires-Dist: ruff<1.0,>=0.4; extra == "dev"
Requires-Dist: black<26.0,>=23.0.0; extra == "dev"
Requires-Dist: isort<7.0,>=5.12; extra == "dev"
Requires-Dist: mypy<2.0,>=1.0; extra == "dev"
Requires-Dist: radon<7.0,>=6.0; extra == "dev"
Requires-Dist: import-linter<3.0,>=2.0; extra == "dev"
Requires-Dist: pre-commit<5.0,>=3.0; extra == "dev"
Requires-Dist: autoflake<3.0,>=2.0; extra == "dev"
Requires-Dist: types-PyYAML<7.0,>=6.0; extra == "dev"
Requires-Dist: build<2.0,>=0.10; extra == "dev"
Requires-Dist: twine<7.0,>=4.0; extra == "dev"
Requires-Dist: pyinstaller<7.0,>=5.0; extra == "dev"
Requires-Dist: urllib3>=2.6.0; extra == "dev"
Dynamic: license-file
